netbox_data_disk/__init__.py
netbox_data_disk/admin.py
netbox_data_disk/api/nested_serializers.py
netbox_data_disk/api/serializers.py
netbox_data_disk/api/urls.py
netbox_data_disk/api/views.py
netbox_data_disk/apps.py
netbox_data_disk/fields/__init__.py
netbox_data_disk/fields/address.py
netbox_data_disk/fields/network.py
netbox_data_disk/filters/__init__.py
netbox_data_disk/filters/nameserver.py
netbox_data_disk/filters/record.py
netbox_data_disk/filters/view.py
netbox_data_disk/filters/zone.py
netbox_data_disk/forms/__init__.py
netbox_data_disk/forms/nameserver.py
netbox_data_disk/forms/record.py
netbox_data_disk/forms/view.py
netbox_data_disk/forms/zone.py
netbox_data_disk/graphql/__init__.py
netbox_data_disk/graphql/nameserver.py
netbox_data_disk/graphql/record.py
netbox_data_disk/graphql/schema.py
netbox_data_disk/graphql/view.py
netbox_data_disk/graphql/zone.py
netbox_data_disk/management/commands/cleanup_database.py
netbox_data_disk/management/commands/update_soa.py
netbox_data_disk/migrations/0001_initial.py
netbox_data_disk/migrations/0001_squashed_netbox_dns_0_15.py
netbox_data_disk/migrations/0002_zone_default_ttl.py
netbox_data_disk/migrations/0003_soa_managed_records.py
netbox_data_disk/migrations/0004_create_ptr_for_a_aaaa_records.py
netbox_data_disk/migrations/0005_update_ns_records.py
netbox_data_disk/migrations/0006_zone_soa_serial_auto.py
netbox_data_disk/migrations/0007_alter_zone_soa_serial_auto.py
netbox_data_disk/migrations/0008_zone_status_names.py
netbox_data_disk/migrations/0009_netbox32.py
netbox_data_disk/migrations/0010_update_soa_records.py
netbox_data_disk/migrations/0011_add_view_model.py
netbox_data_disk/migrations/0012_adjust_zone_and_record.py
netbox_data_disk/migrations/0013_add_nameserver_zone_record_description.py
netbox_data_disk/migrations/0014_add_view_description.py
netbox_data_disk/migrations/0015_add_record_status.py
netbox_data_disk/migrations/0016_cleanup_ptr_records.py
netbox_data_disk-0.0.0.0.18.dist-info/WHEEL
netbox_data_disk-0.0.0.0.18.dist-info/METADATA
netbox_data_disk-0.0.0.0.18.dist-info/RECORD
